odoo/addons/account_coa_menu/README.rst
odoo/addons/account_coa_menu/__init__.py
odoo/addons/account_coa_menu/__manifest__.py
odoo/addons/account_coa_menu/i18n/account_coa_menu.pot
odoo/addons/account_coa_menu/i18n/de.po
odoo/addons/account_coa_menu/i18n/fr.po
odoo/addons/account_coa_menu/i18n/hr.po
odoo/addons/account_coa_menu/i18n/it.po
odoo/addons/account_coa_menu/i18n/pt.po
odoo/addons/account_coa_menu/i18n/sl.po
odoo/addons/account_coa_menu/i18n/tr.po
odoo/addons/account_coa_menu/readme/CONTRIBUTORS.rst
odoo/addons/account_coa_menu/readme/DESCRIPTION.rst
odoo/addons/account_coa_menu/static/description/icon.png
odoo/addons/account_coa_menu/static/description/index.html
odoo/addons/account_coa_menu/views/account_account_template.xml
odoo/addons/account_coa_menu/views/account_chart_template.xml
odoo/addons/account_coa_menu/views/account_fiscal_position_template.xml
odoo/addons/account_coa_menu/views/account_tax_template.xml
odoo/addons/account_coa_menu/views/menu.xml
odoo12_addon_account_coa_menu-12.0.1.0.0.99.dev17.dist-info/METADATA
odoo12_addon_account_coa_menu-12.0.1.0.0.99.dev17.dist-info/WHEEL
odoo12_addon_account_coa_menu-12.0.1.0.0.99.dev17.dist-info/top_level.txt
odoo12_addon_account_coa_menu-12.0.1.0.0.99.dev17.dist-info/RECORD
